drlpp/__init__.py
drlpp/__main__.py
drlpp/core.py
drlpp/drlpp.py
drlpp-0.1.dist-info/METADATA
drlpp-0.1.dist-info/WHEEL
drlpp-0.1.dist-info/entry_points.txt
drlpp-0.1.dist-info/top_level.txt
drlpp-0.1.dist-info/RECORD
