Metadata-Version: 2.1
Name: drlpp
Version: 0.1
Summary: Dynamic Resource Locator Protocol for Python
Home-page: http://github.com/yesmyc/drlpp
Author: ltaoit
Author-email: ltaoist6@gmail.com
License: GPLv3
Platform: UNKNOWN
